<annotation>
	<folder>images</folder>
	<filename>UID_1_5_1_all.jpg</filename>
	<path>C:\Users\leodominick\Desktop\Leukemia Classification\training\images\UID_1_5_1_all.jpg</path>
	<source>
		<database>Unknown</database>
	</source>
	<size>
		<width>450</width>
		<height>450</height>
		<depth>3</depth>
	</size>
	<segmented>0</segmented>
	<object>
		<name>ALL</name>
		<pose>Unspecified</pose>
		<truncated>0</truncated>
		<difficult>0</difficult>
		<bndbox>
			<xmin>101</xmin>
			<ymin>114</ymin>
			<xmax>340</xmax>
			<ymax>352</ymax>
		</bndbox>
	</object>
</annotation>
